{
  "113128": {
    "ID": "113128",
    "Name": "FIG &amp; OLIVE Newport Beach",
    "Reservations": [
      {
        "Time": "06:45PM",
        "URL": "https://opentable.com/book/validate?rid=113128&d=2017-07-21 18:45&p=2&pt=100&ss=0&sd=2017-07-21 18:45&pofids=&hash=1221875570"
      },
      {
        "Time": "07:45PM",
        "URL": "https://opentable.com/book/validate?rid=113128&d=2017-07-21 19:45&p=2&pt=100&ss=0&sd=2017-07-21 19:45&pofids=&hash=1692405802"
      },
      {
        "Time": "08:00PM",
        "URL": "https://opentable.com/book/validate?rid=113128&d=2017-07-21 20:00&p=2&pt=100&ss=0&sd=2017-07-21 20:00&pofids=&hash=3716042717"
      }
    ]
  },
  "145639": {
    "ID": "145639",
    "Name": "CUCINA enoteca - Newport Beach",
    "Reservations": [
      {
        "Time": "07:00PM",
        "URL": "https://opentable.com/book/validate?rid=145639&d=2017-07-21 19:00&p=2&pt=100&ss=0&sd=2017-07-21 19:00&pofids=&hash=39541917"
      },
      {
        "Time": "07:15PM",
        "URL": "https://opentable.com/book/validate?rid=145639&d=2017-07-21 19:15&p=2&pt=100&ss=0&sd=2017-07-21 19:15&pofids=&hash=815288298"
      },
      {
        "Time": "07:30PM",
        "URL": "https://opentable.com/book/validate?rid=145639&d=2017-07-21 19:30&p=2&pt=100&ss=0&sd=2017-07-21 19:30&pofids=&hash=3987429093"
      }
    ]
  },
  "149968": {
    "ID": "149968",
    "Name": "BRIO Tuscan Grille - Irvine - Spectrum Center",
    "Reservations": [
      {
        "Time": "06:45PM",
        "URL": "https://opentable.com/book/validate?rid=149968&d=2017-07-21 18:45&p=2&pt=100&ss=0&sd=2017-07-21 18:45&pofids=&hash=273179360"
      },
      {
        "Time": "07:15PM",
        "URL": "https://opentable.com/book/validate?rid=149968&d=2017-07-21 19:15&p=2&pt=100&ss=0&sd=2017-07-21 19:15&pofids=&hash=3942676546"
      },
      {
        "Time": "07:30PM",
        "URL": "https://opentable.com/book/validate?rid=149968&d=2017-07-21 19:30&p=2&pt=100&ss=0&sd=2017-07-21 19:30&pofids=&hash=3089604003"
      }
    ]
  },
  "15082": {
    "ID": "15082",
    "Name": "Maggiano&#39;s - South Coast Plaza",
    "Reservations": [
      {
        "Time": "06:45PM",
        "URL": "https://opentable.com/book/validate?rid=15082&d=2017-07-21 18:45&p=2&pt=100&ss=0&sd=2017-07-21 18:45&pofids=&hash=1884321144"
      },
      {
        "Time": "07:15PM",
        "URL": "https://opentable.com/book/validate?rid=15082&d=2017-07-21 19:15&p=2&pt=100&ss=0&sd=2017-07-21 19:15&pofids=&hash=2680577217"
      },
      {
        "Time": "07:30PM",
        "URL": "https://opentable.com/book/validate?rid=15082&d=2017-07-21 19:30&p=2&pt=100&ss=0&sd=2017-07-21 19:30&pofids=&hash=344175727"
      }
    ]
  },
  "159592": {
    "ID": "159592",
    "Name": "Pirozzi",
    "Reservations": [
      {
        "Time": "08:00PM",
        "URL": "https://opentable.com/book/validate?rid=159592&d=2017-07-21 20:00&p=2&pt=100&ss=0&sd=2017-07-21 20:00&pofids=&hash=188432145"
      },
      {
        "Time": "08:30PM",
        "URL": "https://opentable.com/book/validate?rid=159592&d=2017-07-21 20:30&p=2&pt=100&ss=0&sd=2017-07-21 20:30&pofids=&hash=2673259894"
      }
    ]
  },
  "190102": {
    "ID": "190102",
    "Name": "North Italia – Irvine",
    "Reservations": [
      {
        "Time": "09:00PM",
        "URL": "https://opentable.com/book/validate?rid=190102&d=2017-07-21 21:00&p=2&pt=100&ss=0&sd=2017-07-21 21:00&pofids=&hash=981740796"
      },
      {
        "Time": "09:15PM",
        "URL": "https://opentable.com/book/validate?rid=190102&d=2017-07-21 21:15&p=2&pt=100&ss=0&sd=2017-07-21 21:15&pofids=&hash=440827183"
      }
    ]
  },
  "191119": {
    "ID": "191119",
    "Name": "il Barone Ristorante",
    "Reservations": [
      {
        "Time": "06:45PM",
        "URL": "https://opentable.com/book/validate?rid=191119&d=2017-07-21 18:45&p=2&pt=100&ss=0&sd=2017-07-21 18:45&pofids=&hash=3353306202"
      },
      {
        "Time": "07:15PM",
        "URL": "https://opentable.com/book/validate?rid=191119&d=2017-07-21 19:15&p=2&pt=100&ss=0&sd=2017-07-21 19:15&pofids=&hash=1741261571"
      },
      {
        "Time": "07:30PM",
        "URL": "https://opentable.com/book/validate?rid=191119&d=2017-07-21 19:30&p=2&pt=100&ss=0&sd=2017-07-21 19:30&pofids=&hash=611918245"
      }
    ]
  },
  "19369": {
    "ID": "19369",
    "Name": "Buca di Beppo - Anaheim",
    "Reservations": [
      {
        "Time": "06:45PM",
        "URL": "https://opentable.com/book/validate?rid=19369&d=2017-07-21 18:45&p=2&pt=100&ss=0&sd=2017-07-21 18:45&pofids=&hash=1171234424"
      },
      {
        "Time": "07:00PM",
        "URL": "https://opentable.com/book/validate?rid=19369&d=2017-07-21 19:00&p=2&pt=100&ss=0&sd=2017-07-21 19:00&pofids=&hash=611216389"
      },
      {
        "Time": "07:15PM",
        "URL": "https://opentable.com/book/validate?rid=19369&d=2017-07-21 19:15&p=2&pt=100&ss=0&sd=2017-07-21 19:15&pofids=&hash=1053099826"
      },
      {
        "Time": "07:30PM",
        "URL": "https://opentable.com/book/validate?rid=19369&d=2017-07-21 19:30&p=2&pt=100&ss=0&sd=2017-07-21 19:30&pofids=&hash=952747842"
      }
    ]
  },
  "195286": {
    "ID": "195286",
    "Name": "Cucina Alessa - Newport Beach",
    "Reservations": [
      {
        "Time": "06:45PM",
        "URL": "https://opentable.com/book/validate?rid=195286&d=2017-07-21 18:45&p=2&pt=100&ss=0&sd=2017-07-21 18:45&pofids=&hash=3340727831"
      },
      {
        "Time": "07:15PM",
        "URL": "https://opentable.com/book/validate?rid=195286&d=2017-07-21 19:15&p=2&pt=100&ss=0&sd=2017-07-21 19:15&pofids=&hash=1068540147"
      },
      {
        "Time": "07:30PM",
        "URL": "https://opentable.com/book/validate?rid=195286&d=2017-07-21 19:30&p=2&pt=100&ss=0&sd=2017-07-21 19:30&pofids=&hash=1689143304"
      }
    ]
  },
  "201415": {
    "ID": "201415",
    "Name": "Il Dolce",
    "Reservations": [
      {
        "Time": "06:45PM",
        "URL": "https://opentable.com/book/validate?rid=201415&d=2017-07-21 18:45&p=2&pt=100&ss=0&sd=2017-07-21 18:45&pofids=&hash=3921383543"
      },
      {
        "Time": "07:00PM",
        "URL": "https://opentable.com/book/validate?rid=201415&d=2017-07-21 19:00&p=2&pt=100&ss=0&sd=2017-07-21 19:00&pofids=&hash=3776531616"
      },
      {
        "Time": "07:15PM",
        "URL": "https://opentable.com/book/validate?rid=201415&d=2017-07-21 19:15&p=2&pt=100&ss=0&sd=2017-07-21 19:15&pofids=&hash=506161364"
      },
      {
        "Time": "07:30PM",
        "URL": "https://opentable.com/book/validate?rid=201415&d=2017-07-21 19:30&p=2&pt=100&ss=0&sd=2017-07-21 19:30&pofids=&hash=1131033274"
      }
    ]
  },
  "202003": {
    "ID": "202003",
    "Name": "Settebello Pizzeria Napoletana - Newport",
    "Reservations": [
      {
        "Time": "07:00PM",
        "URL": "https://opentable.com/book/validate?rid=202003&d=2017-07-21 19:00&p=2&pt=100&ss=0&sd=2017-07-21 19:00&pofids=&hash=825839172"
      },
      {
        "Time": "07:15PM",
        "URL": "https://opentable.com/book/validate?rid=202003&d=2017-07-21 19:15&p=2&pt=100&ss=0&sd=2017-07-21 19:15&pofids=&hash=135305162"
      },
      {
        "Time": "07:45PM",
        "URL": "https://opentable.com/book/validate?rid=202003&d=2017-07-21 19:45&p=2&pt=100&ss=0&sd=2017-07-21 19:45&pofids=&hash=380598500"
      }
    ]
  },
  "209677": {
    "ID": "209677",
    "Name": "Da Bianca Trattoria",
    "Reservations": [
      {
        "Time": "07:45PM",
        "URL": "https://opentable.com/book/validate?rid=209677&d=2017-07-21 19:45&p=2&pt=100&ss=0&sd=2017-07-21 19:45&pofids=&hash=2852423791"
      },
      {
        "Time": "08:00PM",
        "URL": "https://opentable.com/book/validate?rid=209677&d=2017-07-21 20:00&p=2&pt=100&ss=0&sd=2017-07-21 20:00&pofids=&hash=2039068923"
      }
    ]
  },
  "211606": {
    "ID": "211606",
    "Name": "Angelina&#39;s Pizzeria Napoletana- Irvine",
    "Reservations": [
      {
        "Time": "07:45PM",
        "URL": "https://opentable.com/book/validate?rid=211606&d=2017-07-21 19:45&p=2&pt=100&ss=0&sd=2017-07-21 19:45&pofids=&hash=1776898622"
      },
      {
        "Time": "08:00PM",
        "URL": "https://opentable.com/book/validate?rid=211606&d=2017-07-21 20:00&p=2&pt=100&ss=0&sd=2017-07-21 20:00&pofids=&hash=3081967103"
      }
    ]
  },
  "213400": {
    "ID": "213400",
    "Name": "Restaurant at Tustin Ranch Golf Club",
    "Reservations": [
      {
        "Time": "06:45PM",
        "URL": "https://opentable.com/book/validate?rid=213400&d=2017-07-21 18:45&p=2&pt=100&ss=0&sd=2017-07-21 18:45&pofids=&hash=813975336"
      },
      {
        "Time": "07:00PM",
        "URL": "https://opentable.com/book/validate?rid=213400&d=2017-07-21 19:00&p=2&pt=100&ss=0&sd=2017-07-21 19:00&pofids=&hash=514581388"
      },
      {
        "Time": "07:15PM",
        "URL": "https://opentable.com/book/validate?rid=213400&d=2017-07-21 19:15&p=2&pt=100&ss=0&sd=2017-07-21 19:15&pofids=&hash=3269265259"
      },
      {
        "Time": "07:30PM",
        "URL": "https://opentable.com/book/validate?rid=213400&d=2017-07-21 19:30&p=2&pt=100&ss=0&sd=2017-07-21 19:30&pofids=&hash=595336433"
      }
    ]
  },
  "213970": {
    "ID": "213970",
    "Name": "Ruscello - Nordstrom South Coast Plaza",
    "Reservations": [
      {
        "Time": "06:45PM",
        "URL": "https://opentable.com/book/validate?rid=213970&d=2017-07-21 18:45&p=2&pt=100&ss=0&sd=2017-07-21 18:45&pofids=&hash=1642133404"
      },
      {
        "Time": "07:00PM",
        "URL": "https://opentable.com/book/validate?rid=213970&d=2017-07-21 19:00&p=2&pt=100&ss=0&sd=2017-07-21 19:00&pofids=&hash=1183839122"
      },
      {
        "Time": "07:15PM",
        "URL": "https://opentable.com/book/validate?rid=213970&d=2017-07-21 19:15&p=2&pt=100&ss=0&sd=2017-07-21 19:15&pofids=&hash=2630736368"
      },
      {
        "Time": "07:30PM",
        "URL": "https://opentable.com/book/validate?rid=213970&d=2017-07-21 19:30&p=2&pt=100&ss=0&sd=2017-07-21 19:30&pofids=&hash=2785185025"
      }
    ]
  },
  "24628": {
    "ID": "24628",
    "Name": "Andrea at Pelican Hill",
    "Reservations": [
      {
        "Time": "07:45PM",
        "URL": "https://opentable.com/book/validate?rid=24628&d=2017-07-21 19:45&p=2&pt=100&ss=0&sd=2017-07-21 19:45&pofids=&hash=3015631894"
      },
      {
        "Time": "08:00PM",
        "URL": "https://opentable.com/book/validate?rid=24628&d=2017-07-21 20:00&p=2&pt=100&ss=0&sd=2017-07-21 20:00&pofids=&hash=1388070848"
      }
    ]
  },
  "25867": {
    "ID": "25867",
    "Name": "Canaletto Ristorante Veneto",
    "Reservations": [
      {
        "Time": "06:45PM",
        "URL": "https://opentable.com/book/validate?rid=25867&d=2017-07-21 18:45&p=2&pt=100&ss=0&sd=2017-07-21 18:45&pofids=&hash=3699482902"
      },
      {
        "Time": "07:15PM",
        "URL": "https://opentable.com/book/validate?rid=25867&d=2017-07-21 19:15&p=2&pt=100&ss=0&sd=2017-07-21 19:15&pofids=&hash=1380950443"
      },
      {
        "Time": "07:30PM",
        "URL": "https://opentable.com/book/validate?rid=25867&d=2017-07-21 19:30&p=2&pt=100&ss=0&sd=2017-07-21 19:30&pofids=&hash=3583993907"
      }
    ]
  },
  "268051": {
    "ID": "268051",
    "Name": "Water Grill - South Coast Plaza",
    "Reservations": [
      {
        "Time": "06:45PM",
        "URL": "https://opentable.com/book/validate?rid=268051&d=2017-07-21 18:45&p=2&pt=100&ss=0&sd=2017-07-21 18:45&pofids=&hash=244164399"
      },
      {
        "Time": "08:00PM",
        "URL": "https://opentable.com/book/validate?rid=268051&d=2017-07-21 20:00&p=2&pt=100&ss=0&sd=2017-07-21 20:00&pofids=&hash=1402431661"
      },
      {
        "Time": "08:15PM",
        "URL": "https://opentable.com/book/validate?rid=268051&d=2017-07-21 20:15&p=2&pt=100&ss=0&sd=2017-07-21 20:15&pofids=&hash=2516304602"
      }
    ]
  },
  "27205": {
    "ID": "27205",
    "Name": "Andrei&#39;s",
    "Reservations": [
      {
        "Time": "06:45PM",
        "URL": "https://opentable.com/book/validate?rid=27205&d=2017-07-21 18:45&p=2&pt=100&ss=0&sd=2017-07-21 18:45&pofids=&hash=1415539324"
      },
      {
        "Time": "07:00PM",
        "URL": "https://opentable.com/book/validate?rid=27205&d=2017-07-21 19:00&p=2&pt=100&ss=0&sd=2017-07-21 19:00&pofids=&hash=1693943485"
      },
      {
        "Time": "07:15PM",
        "URL": "https://opentable.com/book/validate?rid=27205&d=2017-07-21 19:15&p=2&pt=100&ss=0&sd=2017-07-21 19:15&pofids=&hash=738133019"
      },
      {
        "Time": "07:30PM",
        "URL": "https://opentable.com/book/validate?rid=27205&d=2017-07-21 19:30&p=2&pt=100&ss=0&sd=2017-07-21 19:30&pofids=&hash=2180911537"
      }
    ]
  },
  "28861": {
    "ID": "28861",
    "Name": "Pizzeria Ortica",
    "Reservations": [
      {
        "Time": "07:45PM",
        "URL": "https://opentable.com/book/validate?rid=28861&d=2017-07-21 19:45&p=2&pt=100&ss=0&sd=2017-07-21 19:45&pofids=&hash=1393376216"
      },
      {
        "Time": "08:00PM",
        "URL": "https://opentable.com/book/validate?rid=28861&d=2017-07-21 20:00&p=2&pt=100&ss=0&sd=2017-07-21 20:00&pofids=&hash=4087929524"
      }
    ]
  },
  "3308": {
    "ID": "3308",
    "Name": "Antonello Ristorante",
    "Reservations": [
      {
        "Time": "07:45PM",
        "URL": "https://opentable.com/book/validate?rid=3308&d=2017-07-21 19:45&p=2&pt=100&ss=0&sd=2017-07-21 19:45&pofids=&hash=3518004241"
      },
      {
        "Time": "08:00PM",
        "URL": "https://opentable.com/book/validate?rid=3308&d=2017-07-21 20:00&p=2&pt=100&ss=0&sd=2017-07-21 20:00&pofids=&hash=3921799965"
      }
    ]
  },
  "33847": {
    "ID": "33847",
    "Name": "Gulliver&#39;s Restaurant",
    "Reservations": [
      {
        "Time": "06:45PM",
        "URL": "https://opentable.com/book/validate?rid=33847&d=2017-07-21 18:45&p=2&pt=100&ss=0&sd=2017-07-21 18:45&pofids=&hash=1851129639"
      },
      {
        "Time": "07:00PM",
        "URL": "https://opentable.com/book/validate?rid=33847&d=2017-07-21 19:00&p=2&pt=100&ss=0&sd=2017-07-21 19:00&pofids=&hash=2673948143"
      },
      {
        "Time": "07:15PM",
        "URL": "https://opentable.com/book/validate?rid=33847&d=2017-07-21 19:15&p=2&pt=100&ss=0&sd=2017-07-21 19:15&pofids=&hash=946711246"
      },
      {
        "Time": "07:30PM",
        "URL": "https://opentable.com/book/validate?rid=33847&d=2017-07-21 19:30&p=2&pt=100&ss=0&sd=2017-07-21 19:30&pofids=&hash=926407072"
      }
    ]
  },
  "37081": {
    "ID": "37081",
    "Name": "Modo Mio - Newport Coast",
    "Reservations": [
      {
        "Time": "07:45PM",
        "URL": "https://opentable.com/book/validate?rid=37081&d=2017-07-21 19:45&p=2&pt=100&ss=0&sd=2017-07-21 19:45&pofids=&hash=4037148605"
      },
      {
        "Time": "08:15PM",
        "URL": "https://opentable.com/book/validate?rid=37081&d=2017-07-21 20:15&p=2&pt=100&ss=0&sd=2017-07-21 20:15&pofids=&hash=2490694284"
      }
    ]
  },
  "3963": {
    "ID": "3963",
    "Name": "Il Fornaio - Irvine",
    "Reservations": [
      {
        "Time": "06:45PM",
        "URL": "https://opentable.com/book/validate?rid=3963&d=2017-07-21 18:45&p=2&pt=100&ss=0&sd=2017-07-21 18:45&pofids=&hash=171359503"
      },
      {
        "Time": "07:00PM",
        "URL": "https://opentable.com/book/validate?rid=3963&d=2017-07-21 19:00&p=2&pt=100&ss=0&sd=2017-07-21 19:00&pofids=&hash=1550785403"
      },
      {
        "Time": "07:15PM",
        "URL": "https://opentable.com/book/validate?rid=3963&d=2017-07-21 19:15&p=2&pt=100&ss=0&sd=2017-07-21 19:15&pofids=&hash=2620360281"
      },
      {
        "Time": "07:30PM",
        "URL": "https://opentable.com/book/validate?rid=3963&d=2017-07-21 19:30&p=2&pt=100&ss=0&sd=2017-07-21 19:30&pofids=&hash=3062008878"
      }
    ]
  },
  "42475": {
    "ID": "42475",
    "Name": "Tusca - Hyatt Regency Orange County",
    "Reservations": [
      {
        "Time": "06:45PM",
        "URL": "https://opentable.com/book/validate?rid=42475&d=2017-07-21 18:45&p=2&pt=100&ss=0&sd=2017-07-21 18:45&pofids=&hash=156372936"
      },
      {
        "Time": "07:00PM",
        "URL": "https://opentable.com/book/validate?rid=42475&d=2017-07-21 19:00&p=2&pt=100&ss=0&sd=2017-07-21 19:00&pofids=&hash=3077341764"
      },
      {
        "Time": "07:15PM",
        "URL": "https://opentable.com/book/validate?rid=42475&d=2017-07-21 19:15&p=2&pt=100&ss=0&sd=2017-07-21 19:15&pofids=&hash=1027096358"
      },
      {
        "Time": "07:30PM",
        "URL": "https://opentable.com/book/validate?rid=42475&d=2017-07-21 19:30&p=2&pt=100&ss=0&sd=2017-07-21 19:30&pofids=&hash=3634836737"
      }
    ]
  },
  "443413": {
    "ID": "443413",
    "Name": "Canapa Farms ",
    "Reservations": [
      {
        "Time": "06:45PM",
        "URL": "https://opentable.com/book/validate?rid=443413&d=2017-07-21 18:45&p=2&pt=100&ss=0&sd=2017-07-21 18:45&pofids=&hash=1845224144"
      },
      {
        "Time": "07:00PM",
        "URL": "https://opentable.com/book/validate?rid=443413&d=2017-07-21 19:00&p=2&pt=100&ss=0&sd=2017-07-21 19:00&pofids=&hash=3145865730"
      },
      {
        "Time": "07:15PM",
        "URL": "https://opentable.com/book/validate?rid=443413&d=2017-07-21 19:15&p=2&pt=100&ss=0&sd=2017-07-21 19:15&pofids=&hash=3317121387"
      },
      {
        "Time": "07:30PM",
        "URL": "https://opentable.com/book/validate?rid=443413&d=2017-07-21 19:30&p=2&pt=100&ss=0&sd=2017-07-21 19:30&pofids=&hash=286398045"
      }
    ]
  },
  "443686": {
    "ID": "443686",
    "Name": "Caffe Pinguini",
    "Reservations": [
      {
        "Time": "06:45PM",
        "URL": "https://opentable.com/book/validate?rid=443686&d=2017-07-21 18:45&p=2&pt=100&ss=0&sd=2017-07-21 18:45&pofids=&hash=3755644172"
      },
      {
        "Time": "07:00PM",
        "URL": "https://opentable.com/book/validate?rid=443686&d=2017-07-21 19:00&p=2&pt=100&ss=0&sd=2017-07-21 19:00&pofids=&hash=4163396769"
      },
      {
        "Time": "07:15PM",
        "URL": "https://opentable.com/book/validate?rid=443686&d=2017-07-21 19:15&p=2&pt=100&ss=0&sd=2017-07-21 19:15&pofids=&hash=4290833147"
      },
      {
        "Time": "07:30PM",
        "URL": "https://opentable.com/book/validate?rid=443686&d=2017-07-21 19:30&p=2&pt=100&ss=0&sd=2017-07-21 19:30&pofids=&hash=557265649"
      }
    ]
  },
  "45121": {
    "ID": "45121",
    "Name": "Great Maple - Fashion Island",
    "Reservations": [
      {
        "Time": "07:00PM",
        "URL": "https://opentable.com/book/validate?rid=45121&d=2017-07-21 19:00&p=2&pt=100&ss=0&sd=2017-07-21 19:00&pofids=&hash=1922394832"
      },
      {
        "Time": "08:00PM",
        "URL": "https://opentable.com/book/validate?rid=45121&d=2017-07-21 20:00&p=2&pt=100&ss=0&sd=2017-07-21 20:00&pofids=&hash=425996485"
      }
    ]
  },
  "47446": {
    "ID": "47446",
    "Name": "Rothschild&#39;s Restaurant",
    "Reservations": [
      {
        "Time": "06:45PM",
        "URL": "https://opentable.com/book/validate?rid=47446&d=2017-07-21 18:45&p=2&pt=100&ss=0&sd=2017-07-21 18:45&pofids=&hash=4171022085"
      },
      {
        "Time": "07:00PM",
        "URL": "https://opentable.com/book/validate?rid=47446&d=2017-07-21 19:00&p=2&pt=100&ss=0&sd=2017-07-21 19:00&pofids=&hash=1696580916"
      },
      {
        "Time": "07:15PM",
        "URL": "https://opentable.com/book/validate?rid=47446&d=2017-07-21 19:15&p=2&pt=100&ss=0&sd=2017-07-21 19:15&pofids=&hash=3747261501"
      },
      {
        "Time": "07:30PM",
        "URL": "https://opentable.com/book/validate?rid=47446&d=2017-07-21 19:30&p=2&pt=100&ss=0&sd=2017-07-21 19:30&pofids=&hash=974493990"
      }
    ]
  },
  "5297": {
    "ID": "5297",
    "Name": "Juliette",
    "Reservations": [
      {
        "Time": "06:45PM",
        "URL": "https://opentable.com/book/validate?rid=5297&d=2017-07-21 18:45&p=2&pt=100&ss=0&sd=2017-07-21 18:45&pofids=&hash=2427309240"
      },
      {
        "Time": "07:15PM",
        "URL": "https://opentable.com/book/validate?rid=5297&d=2017-07-21 19:15&p=2&pt=100&ss=0&sd=2017-07-21 19:15&pofids=&hash=650490525"
      },
      {
        "Time": "07:30PM",
        "URL": "https://opentable.com/book/validate?rid=5297&d=2017-07-21 19:30&p=2&pt=100&ss=0&sd=2017-07-21 19:30&pofids=&hash=1590326574"
      }
    ]
  },
  "55453": {
    "ID": "55453",
    "Name": "Taco Rosa - Irvine",
    "Reservations": [
      {
        "Time": "06:45PM",
        "URL": "https://opentable.com/book/validate?rid=55453&d=2017-07-21 18:45&p=2&pt=100&ss=0&sd=2017-07-21 18:45&pofids=&hash=29509934"
      },
      {
        "Time": "07:00PM",
        "URL": "https://opentable.com/book/validate?rid=55453&d=2017-07-21 19:00&p=2&pt=100&ss=0&sd=2017-07-21 19:00&pofids=&hash=3037762853"
      },
      {
        "Time": "07:15PM",
        "URL": "https://opentable.com/book/validate?rid=55453&d=2017-07-21 19:15&p=2&pt=100&ss=0&sd=2017-07-21 19:15&pofids=&hash=2673070027"
      },
      {
        "Time": "07:30PM",
        "URL": "https://opentable.com/book/validate?rid=55453&d=2017-07-21 19:30&p=2&pt=100&ss=0&sd=2017-07-21 19:30&pofids=&hash=2699780362"
      }
    ]
  },
  "62098": {
    "ID": "62098",
    "Name": "Newport Rib Company",
    "Reservations": [
      {
        "Time": "06:45PM",
        "URL": "https://opentable.com/book/validate?rid=62098&d=2017-07-21 18:45&p=2&pt=100&ss=0&sd=2017-07-21 18:45&pofids=&hash=2543802639"
      },
      {
        "Time": "07:00PM",
        "URL": "https://opentable.com/book/validate?rid=62098&d=2017-07-21 19:00&p=2&pt=100&ss=0&sd=2017-07-21 19:00&pofids=&hash=632772196"
      },
      {
        "Time": "07:15PM",
        "URL": "https://opentable.com/book/validate?rid=62098&d=2017-07-21 19:15&p=2&pt=100&ss=0&sd=2017-07-21 19:15&pofids=&hash=4269892496"
      },
      {
        "Time": "07:30PM",
        "URL": "https://opentable.com/book/validate?rid=62098&d=2017-07-21 19:30&p=2&pt=100&ss=0&sd=2017-07-21 19:30&pofids=&hash=3790292081"
      }
    ]
  },
  "64888": {
    "ID": "64888",
    "Name": "Sapori Ristorante - Newport Beach",
    "Reservations": [
      {
        "Time": "06:45PM",
        "URL": "https://opentable.com/book/validate?rid=64888&d=2017-07-21 18:45&p=2&pt=100&ss=0&sd=2017-07-21 18:45&pofids=&hash=2158492803"
      },
      {
        "Time": "07:15PM",
        "URL": "https://opentable.com/book/validate?rid=64888&d=2017-07-21 19:15&p=2&pt=100&ss=0&sd=2017-07-21 19:15&pofids=&hash=1241790492"
      },
      {
        "Time": "08:00PM",
        "URL": "https://opentable.com/book/validate?rid=64888&d=2017-07-21 20:00&p=2&pt=100&ss=0&sd=2017-07-21 20:00&pofids=&hash=99800984"
      }
    ]
  },
  "66577": {
    "ID": "66577",
    "Name": "Pina&#39;s Bistro",
    "Reservations": [
      {
        "Time": "06:45PM",
        "URL": "https://opentable.com/book/validate?rid=66577&d=2017-07-21 18:45&p=2&pt=100&ss=0&sd=2017-07-21 18:45&pofids=&hash=656657036"
      },
      {
        "Time": "07:00PM",
        "URL": "https://opentable.com/book/validate?rid=66577&d=2017-07-21 19:00&p=2&pt=100&ss=0&sd=2017-07-21 19:00&pofids=&hash=307897385"
      },
      {
        "Time": "07:15PM",
        "URL": "https://opentable.com/book/validate?rid=66577&d=2017-07-21 19:15&p=2&pt=100&ss=0&sd=2017-07-21 19:15&pofids=&hash=2814158074"
      },
      {
        "Time": "07:30PM",
        "URL": "https://opentable.com/book/validate?rid=66577&d=2017-07-21 19:30&p=2&pt=100&ss=0&sd=2017-07-21 19:30&pofids=&hash=3665083229"
      }
    ]
  },
  "68866": {
    "ID": "68866",
    "Name": "Pizzeria Mozza - Newport Beach",
    "Reservations": [
      {
        "Time": "08:30PM",
        "URL": "https://opentable.com/book/validate?rid=68866&d=2017-07-21 20:30&p=2&pt=100&ss=0&sd=2017-07-21 20:30&pofids=&hash=4077602590"
      },
      {
        "Time": "08:45PM",
        "URL": "https://opentable.com/book/validate?rid=68866&d=2017-07-21 20:45&p=2&pt=100&ss=0&sd=2017-07-21 20:45&pofids=&hash=1069470363"
      }
    ]
  },
  "72307": {
    "ID": "72307",
    "Name": "Onotria Wine Country Cuisine",
    "Reservations": [
      {
        "Time": "06:45PM",
        "URL": "https://opentable.com/book/validate?rid=72307&d=2017-07-21 18:45&p=2&pt=100&ss=0&sd=2017-07-21 18:45&pofids=&hash=3429042556"
      },
      {
        "Time": "07:00PM",
        "URL": "https://opentable.com/book/validate?rid=72307&d=2017-07-21 19:00&p=2&pt=100&ss=0&sd=2017-07-21 19:00&pofids=&hash=1306329331"
      },
      {
        "Time": "07:15PM",
        "URL": "https://opentable.com/book/validate?rid=72307&d=2017-07-21 19:15&p=2&pt=100&ss=0&sd=2017-07-21 19:15&pofids=&hash=3418998040"
      },
      {
        "Time": "07:30PM",
        "URL": "https://opentable.com/book/validate?rid=72307&d=2017-07-21 19:30&p=2&pt=100&ss=0&sd=2017-07-21 19:30&pofids=&hash=1040627081"
      }
    ]
  },
  "76381": {
    "ID": "76381",
    "Name": "CUCINA enoteca - Irvine",
    "Reservations": [
      {
        "Time": "09:00PM",
        "URL": "https://opentable.com/book/validate?rid=76381&d=2017-07-21 21:00&p=2&pt=100&ss=0&sd=2017-07-21 21:00&pofids=&hash=3425741166"
      },
      {
        "Time": "09:15PM",
        "URL": "https://opentable.com/book/validate?rid=76381&d=2017-07-21 21:15&p=2&pt=100&ss=0&sd=2017-07-21 21:15&pofids=&hash=1759856604"
      }
    ]
  }
}
